bridge_mcp.py
bridge_mcp-2.1.0.dist-info/METADATA
bridge_mcp-2.1.0.dist-info/WHEEL
bridge_mcp-2.1.0.dist-info/licenses/LICENSE
bridge_mcp-2.1.0.dist-info/RECORD
