Metadata-Version: 2.4
Name: bridge-mcp
Version: 2.1.0
Summary: Visual Desktop Bridge - Give any AI full control over Windows
Project-URL: Homepage, https://github.com/BarhamAgha1/Bridge-MCP
Author: Barham Agha
License-File: LICENSE
Requires-Python: >=3.10
Requires-Dist: fastmcp>=2.0.0
Requires-Dist: fuzzywuzzy>=0.18.0
Requires-Dist: keyboard>=0.13.5
Requires-Dist: mouse>=0.7.1
Requires-Dist: pillow>=10.0.0
Requires-Dist: psutil>=5.9.0
Requires-Dist: pyautogui>=0.9.54
Requires-Dist: pyperclip>=1.8.2
Requires-Dist: python-levenshtein>=0.21.0
Requires-Dist: uiautomation>=2.0.0
